README.rst
setup.py
kutuzov/__init__.py
kutuzov/__main__.py
kutuzov/version.py
kutuzov.egg-info/PKG-INFO
kutuzov.egg-info/SOURCES.txt
kutuzov.egg-info/dependency_links.txt
kutuzov.egg-info/top_level.txt