Metadata-Version: 1.2
Name: kutuzov
Version: 0.1.0
Summary: Derives type annotations from Sphinx comments in Python source
Home-page: https://github.com/mpenkov/kutuzov
Author: Michael Penkov
Author-email: m@penkov.dev
License: MIT
Download-URL: http://pypi.python.org/pypi/kutuzov
Keywords: sphinx pyannotate napoleon
Platform: any
Classifier: Development Status :: 4 - Beta
Classifier: Environment :: Console
Classifier: Intended Audience :: Developers
Classifier: License :: OSI Approved :: MIT License
Classifier: Operating System :: OS Independent
Classifier: Programming Language :: Python :: 3.5
Classifier: Programming Language :: Python :: 3.6
Classifier: Programming Language :: Python :: 3.7
Classifier: Programming Language :: Python :: 3.8
Classifier: Programming Language :: Python :: 3.9
Requires-Python: >=3.5.*
